{"type":"PR","pr":{"number":8,"head":"44d056719bc7b8f20ba0900c7b155c4ca1f044ba"},"user":"enerqy","status":"draft","branch":"cms/blog/denouement-2019-music","collection":"blog","commitMessage":"Create Post “denouement-2019-music”","title":"Denouement 2019: Music","description":"No Description!","objects":{"entry":{"path":"posts/denouement-2019-music.md","sha":"445f1fbaa90cfffb6317f16bfc99e5bddb7a2336"},"files":[{"path":"static/img/krule.png","sha":"e740d25fcd774d3a78c0396afd3632c5828cfbfe"}]},"timeStamp":"2019-12-30T10:00:53.459Z","version":"1"}